setup.cfg
setup.py
cloud_elements/__init__.py
cloud_elements.egg-info/PKG-INFO
cloud_elements.egg-info/SOURCES.txt
cloud_elements.egg-info/dependency_links.txt
cloud_elements.egg-info/requires.txt
cloud_elements.egg-info/top_level.txt