Metadata-Version: 1.0
Name: cloud-elements
Version: 0.2.2
Summary: Cloud Elements Connector for Python
Home-page: https://github.com/cloud-elements/elements-connector-python.git
Author: Christian Rodriguez
Author-email: christian.etpr10@gmail.com
License: UNKNOWN
Platform: UNKNOWN
